{
    "title" : "八大人觉经",
    "desc" : "<div style='text-align:left'>《八大人觉经》收于大正藏第十七册。本经以说明诸佛菩萨等大人所觉知思惟的八种法。佛弟子须观察体会八大人觉，以作自觉、觉他之修行。<br><br>《八大人觉经》含经题只有三百八十一字，经文简短扼要，易于诵读。<br><br>本经之八大人觉系指觉世间无常、觉多欲、觉心不足、觉懈怠、觉愚痴、觉贫怨、觉欲过患、觉生死。八大人觉在阿含经典、佛遗教经、成实论中均广有论说，其顺序、名称虽异，然旨趣则同。<br><br>证严法师于静思精舍，讲述《八大人觉经》共三次。 讲述融旧入新，以理相系，义理清晰；以事相证，脉络分明。三次时间虽跨越将近二十年，其理其事并无违和，更能见证上人始终如一，倡导「佛法生活化，菩萨人间化」的悲心愿力。尤其对现代与后世的声声呼唤，句句叮咛，语语慈爱，既深入佛法又浅出人间，实实在在就是为时代作见证，为人间写历史，为慈济立经藏。</div>",
    "headimg" : "http://jingsizen.com/img/sutra-medpic.jpg",
    "list" : {
        "type" : "mp3GroupList1",
        "info" :[{
            "groupTitle": "证严法师讲述《八大人觉经》音频 1 -- 10",
            "list": [{
                "title": "《八大人觉经》-01",
                "video": "http://jingsizen.com/audio/8Insights/EightInsights01.mp3"
            }, {
                "title": "《八大人觉经》-02",
                "video": "http://jingsizen.com/audio/8Insights/EightInsights02.mp3"
            }, {
                "title": "《八大人觉经》-03",
                "video": "http://jingsizen.com/audio/8Insights/EightInsights03.mp3"
            }, {
                "title": "《八大人觉经》-04",
                "video": "http://jingsizen.com/audio/8Insights/EightInsights04.mp3"
            }, {
                "title": "《八大人觉经》-05",
                "video": "http://jingsizen.com/audio/8Insights/EightInsights05.mp3"
            }, {
                "title": "《八大人觉经》-06",
                "video": "http://jingsizen.com/audio/8Insights/EightInsights06.mp3"
            }, {
                "title": "《八大人觉经》-07",
                "video": "http://jingsizen.com/audio/8Insights/EightInsights07.mp3"
            }, {
                "title": "《八大人觉经》-08",
                "video": "http://jingsizen.com/audio/8Insights/EightInsights08.mp3"
            }, {
                "title": "《八大人觉经》-09",
                "video": "http://jingsizen.com/audio/8Insights/EightInsights09.mp3"
            }, {
                "title": "《八大人觉经》-10",
                "video": "http://jingsizen.com/audio/8Insights/EightInsights10.mp3"
            }]
        }, {
            "groupTitle": "证严法师讲述《八大人觉经》音频 11 -- 20",
            "list": [{
                "title": "《八大人觉经》-11",
                "video": "http://jingsizen.com/audio/8Insights/EightInsights11.mp3"
            }, {
                "title": "《八大人觉经》-12",
                "video": "http://jingsizen.com/audio/8Insights/EightInsights12.mp3"
            }, {
                "title": "《八大人觉经》-13",
                "video": "http://jingsizen.com/audio/8Insights/EightInsights13.mp3"
            }, {
                "title": "《八大人觉经》-14",
                "video": "http://jingsizen.com/audio/8Insights/EightInsights14.mp3"
            }, {
                "title": "《八大人觉经》-15",
                "video": "http://jingsizen.com/audio/8Insights/EightInsights15.mp3"
            }, {
                "title": "《八大人觉经》-16",
                "video": "http://jingsizen.com/audio/8Insights/EightInsights16.mp3"
            }, {
                "title": "《八大人觉经》-17",
                "video": "http://jingsizen.com/audio/8Insights/EightInsights17.mp3"
            }, {
                "title": "《八大人觉经》-18",
                "video": "http://jingsizen.com/audio/8Insights/EightInsights18.mp3"
            }, {
                "title": "《八大人觉经》-19",
                "video": "http://jingsizen.com/audio/8Insights/EightInsights19.mp3"
            }, {
                "title": "《八大人觉经》-20",
                "video": "http://jingsizen.com/audio/8Insights/EightInsights20.mp3"
            }]
        }, {
            "groupTitle": "证严法师讲述《八大人觉经》音频 21 -- 30",
            "list": [{
                "title": "《八大人觉经》-21",
                "video": "http://jingsizen.com/audio/8Insights/EightInsights21.mp3"
            }, {
                "title": "《八大人觉经》-22",
                "video": "http://jingsizen.com/audio/8Insights/EightInsights22.mp3"
            }, {
                "title": "《八大人觉经》-23",
                "video": "http://jingsizen.com/audio/8Insights/EightInsights23.mp3"
            }, {
                "title": "《八大人觉经》-24",
                "video": "http://jingsizen.com/audio/8Insights/EightInsights24.mp3"
            }, {
                "title": "《八大人觉经》-25",
                "video": "http://jingsizen.com/audio/8Insights/EightInsights25.mp3"
            }, {
                "title": "《八大人觉经》-26",
                "video": "http://jingsizen.com/audio/8Insights/EightInsights26.mp3"
            }, {
                "title": "《八大人觉经》-27",
                "video": "http://jingsizen.com/audio/8Insights/EightInsights27.mp3"
            }, {
                "title": "《八大人觉经》-28",
                "video": "http://jingsizen.com/audio/8Insights/EightInsights28.mp3"
            }, {
                "title": "《八大人觉经》-29",
                "video": "http://jingsizen.com/audio/8Insights/EightInsights29.mp3"
            }, {
                "title": "《八大人觉经》-30",
                "video": "http://jingsizen.com/audio/8Insights/EightInsights30.mp3"
            }]
        }]
    }
}