{
    "title" : "无量义经",
    "desc" : "佛陀讲《法华经》之前，先讲《无量义经》，因为《无量义经》是《法华经》全部的精粹所在，而《法华经》则是《无量义经》的注解。<br><br><a href='https://mp.weixin.qq.com/s/bBJ00dixdgs2xPoPw-hRxA'> ===> 点此了解更多《无量义经》简介 <=== </a>",
    "headimg" : "http://jingsizen.com/img/sutra-medpic.jpg",
    "list" : {
        "type" : "mp3GroupList1",
        "info" : [{
            "groupTitle": "证严法师讲述《无量义经》音频 1 -- 10",
            "list": [{
                "title": "证严法师讲述《无量义经》-01",
                "video": "audio/WuLiangYi/familybooklybook1.mp3"
            }, {
                "title": "证严法师讲述《无量义经》-02",
                "video": "audio/WuLiangYi/familybooklybook2.mp3"
            }, {
                "title": "证严法师讲述《无量义经》-03",
                "video": "audio/WuLiangYi/familybooklybook3.mp3"
            }, {
                "title": "证严法师讲述《无量义经》-04",
                "video": "audio/WuLiangYi/familybooklybook4.mp3"
            }, {
                "title": "证严法师讲述《无量义经》-05",
                "video": "audio/WuLiangYi/familybooklybook5.mp3"
            }, {
                "title": "证严法师讲述《无量义经》-06",
                "video": "audio/WuLiangYi/familybooklybook6.mp3"
            }, {
                "title": "证严法师讲述《无量义经》-07",
                "video": "audio/WuLiangYi/familybooklybook7.mp3"
            }, {
                "title": "证严法师讲述《无量义经》-08",
                "video": "audio/WuLiangYi/familybooklybook8.mp3"
            }, {
                "title": "证严法师讲述《无量义经》-09",
                "video": "audio/WuLiangYi/familybooklybook9.mp3"
            }, {
                "title": "证严法师讲述《无量义经》-10",
                "video": "audio/WuLiangYi/familybooklybook10.mp3"
            }]
        }, {
            "groupTitle": "证严法师讲述《无量义经》音频 11 -- 20",
            "list": [{
                "title": "证严法师讲述《无量义经》-11",
                "video": "audio/WuLiangYi/familybooklybook11.mp3"
            }, {
                "title": "证严法师讲述《无量义经》-12",
                "video": "audio/WuLiangYi/familybooklybook12.mp3"
            }, {
                "title": "证严法师讲述《无量义经》-13",
                "video": "audio/WuLiangYi/familybooklybook13.mp3"
            }, {
                "title": "证严法师讲述《无量义经》-14",
                "video": "audio/WuLiangYi/familybooklybook14.mp3"
            }, {
                "title": "证严法师讲述《无量义经》-15",
                "video": "audio/WuLiangYi/familybooklybook15.mp3"
            }, {
                "title": "证严法师讲述《无量义经》-16",
                "video": "audio/WuLiangYi/familybooklybook16.mp3"
            }, {
                "title": "证严法师讲述《无量义经》-17",
                "video": "audio/WuLiangYi/familybooklybook17.mp3"
            }, {
                "title": "证严法师讲述《无量义经》-18",
                "video": "audio/WuLiangYi/familybooklybook18.mp3"
            }, {
                "title": "证严法师讲述《无量义经》-19",
                "video": "audio/WuLiangYi/familybooklybook19.mp3"
            }, {
                "title": "证严法师讲述《无量义经》-20",
                "video": "audio/WuLiangYi/familybooklybook20.mp3"
            }]
        }, {
            "groupTitle": "证严法师讲述《无量义经》音频 21 -- 30",
            "list": [{
                "title": "证严法师讲述《无量义经》-21",
                "video": "audio/WuLiangYi/familybooklybook21.mp3"
            }, {
                "title": "证严法师讲述《无量义经》-22",
                "video": "audio/WuLiangYi/familybooklybook22.mp3"
            }, {
                "title": "证严法师讲述《无量义经》-23",
                "video": "audio/WuLiangYi/familybooklybook23.mp3"
            }, {
                "title": "证严法师讲述《无量义经》-24",
                "video": "audio/WuLiangYi/familybooklybook24.mp3"
            }, {
                "title": "证严法师讲述《无量义经》-25",
                "video": "audio/WuLiangYi/familybooklybook25.mp3"
            }, {
                "title": "证严法师讲述《无量义经》-26",
                "video": "audio/WuLiangYi/familybooklybook26.mp3"
            }, {
                "title": "证严法师讲述《无量义经》-27",
                "video": "audio/WuLiangYi/familybooklybook27.mp3"
            }, {
                "title": "证严法师讲述《无量义经》-28",
                "video": "audio/WuLiangYi/familybooklybook28.mp3"
            }, {
                "title": "证严法师讲述《无量义经》-29",
                "video": "audio/WuLiangYi/familybooklybook29.mp3"
            }, {
                "title": "证严法师讲述《无量义经》-30",
                "video": "audio/WuLiangYi/familybooklybook30.mp3"
            }]
        }, {
            "groupTitle": "证严法师讲述《无量义经》音频 31 -- 40",
            "list": [{
                "title": "证严法师讲述《无量义经》-31",
                "video": "audio/WuLiangYi/familybooklybook31.mp3"
            }, {
                "title": "证严法师讲述《无量义经》-32",
                "video": "audio/WuLiangYi/familybooklybook32.mp3"
            }, {
                "title": "证严法师讲述《无量义经》-33",
                "video": "audio/WuLiangYi/familybooklybook33.mp3"
            }, {
                "title": "证严法师讲述《无量义经》-34",
                "video": "audio/WuLiangYi/familybooklybook34.mp3"
            }, {
                "title": "证严法师讲述《无量义经》-35",
                "video": "audio/WuLiangYi/familybooklybook35.mp3"
            }, {
                "title": "证严法师讲述《无量义经》-36",
                "video": "audio/WuLiangYi/familybooklybook36.mp3"
            }, {
                "title": "证严法师讲述《无量义经》-37",
                "video": "audio/WuLiangYi/familybooklybook37.mp3"
            }, {
                "title": "证严法师讲述《无量义经》-38",
                "video": "audio/WuLiangYi/familybooklybook38.mp3"
            }, {
                "title": "证严法师讲述《无量义经》-39",
                "video": "audio/WuLiangYi/familybooklybook39.mp3"
            }, {
                "title": "证严法师讲述《无量义经》-40",
                "video": "audio/WuLiangYi/familybooklybook40.mp3"
            }]
        }, {
            "groupTitle": "证严法师讲述《无量义经》音频 41 -- 50",
            "list": [{
                "title": "证严法师讲述《无量义经》-41",
                "video": "audio/WuLiangYi/familybooklybook41.mp3"
            }, {
                "title": "证严法师讲述《无量义经》-42",
                "video": "audio/WuLiangYi/familybooklybook42.mp3"
            }, {
                "title": "证严法师讲述《无量义经》-43",
                "video": "audio/WuLiangYi/familybooklybook43.mp3"
            }, {
                "title": "证严法师讲述《无量义经》-44",
                "video": "audio/WuLiangYi/familybooklybook44.mp3"
            }, {
                "title": "证严法师讲述《无量义经》-45",
                "video": "audio/WuLiangYi/familybooklybook45.mp3"
            }, {
                "title": "证严法师讲述《无量义经》-46",
                "video": "audio/WuLiangYi/familybooklybook46.mp3"
            }, {
                "title": "证严法师讲述《无量义经》-47",
                "video": "audio/WuLiangYi/familybooklybook47.mp3"
            }, {
                "title": "证严法师讲述《无量义经》-48",
                "video": "audio/WuLiangYi/familybooklybook48.mp3"
            }, {
                "title": "证严法师讲述《无量义经》-49",
                "video": "audio/WuLiangYi/familybooklybook49.mp3"
            }, {
                "title": "证严法师讲述《无量义经》-50",
                "video": "audio/WuLiangYi/familybooklybook50.mp3"
            }]
        }, {
            "groupTitle": "证严法师讲述《无量义经》音频 51 -- 60",
            "list": [{
                "title": "证严法师讲述《无量义经》-51",
                "video": "audio/WuLiangYi/familybooklybook51.mp3"
            }, {
                "title": "证严法师讲述《无量义经》-52",
                "video": "audio/WuLiangYi/familybooklybook52.mp3"
            }, {
                "title": "证严法师讲述《无量义经》-53",
                "video": "audio/WuLiangYi/familybooklybook53.mp3"
            }, {
                "title": "证严法师讲述《无量义经》-54",
                "video": "audio/WuLiangYi/familybooklybook54.mp3"
            }, {
                "title": "证严法师讲述《无量义经》-55",
                "video": "audio/WuLiangYi/familybooklybook55.mp3"
            }, {
                "title": "证严法师讲述《无量义经》-56",
                "video": "audio/WuLiangYi/familybooklybook56.mp3"
            }, {
                "title": "证严法师讲述《无量义经》-57",
                "video": "audio/WuLiangYi/familybooklybook57.mp3"
            }, {
                "title": "证严法师讲述《无量义经》-58",
                "video": "audio/WuLiangYi/familybooklybook58.mp3"
            }, {
                "title": "证严法师讲述《无量义经》-59",
                "video": "audio/WuLiangYi/familybooklybook59.mp3"
            }, {
                "title": "证严法师讲述《无量义经》-60",
                "video": "audio/WuLiangYi/familybooklybook60.mp3"
            }]
        }, {
            "groupTitle": "证严法师讲述《无量义经》音频 61 -- 70",
            "list": [{
                "title": "证严法师讲述《无量义经》-61",
                "video": "audio/WuLiangYi/familybooklybook61.mp3"
            }, {
                "title": "证严法师讲述《无量义经》-62",
                "video": "audio/WuLiangYi/familybooklybook62.mp3"
            }, {
                "title": "证严法师讲述《无量义经》-63",
                "video": "audio/WuLiangYi/familybooklybook63.mp3"
            }, {
                "title": "证严法师讲述《无量义经》-64",
                "video": "audio/WuLiangYi/familybooklybook64.mp3"
            }, {
                "title": "证严法师讲述《无量义经》-65",
                "video": "audio/WuLiangYi/familybooklybook65.mp3"
            }, {
                "title": "证严法师讲述《无量义经》-66",
                "video": "audio/WuLiangYi/familybooklybook66.mp3"
            }, {
                "title": "证严法师讲述《无量义经》-67",
                "video": "audio/WuLiangYi/familybooklybook67.mp3"
            }, {
                "title": "证严法师讲述《无量义经》-68",
                "video": "audio/WuLiangYi/familybooklybook68.mp3"
            }, {
                "title": "证严法师讲述《无量义经》-69",
                "video": "audio/WuLiangYi/familybooklybook69.mp3"
            }, {
                "title": "证严法师讲述《无量义经》-70",
                "video": "audio/WuLiangYi/familybooklybook70.mp3"
            }]
        }, {
            "groupTitle": "证严法师讲述《无量义经》音频 71 -- 78",
            "list": [{
                "title": "证严法师讲述《无量义经》-71",
                "video": "audio/WuLiangYi/familybooklybook71.mp3"
            }, {
                "title": "证严法师讲述《无量义经》-72",
                "video": "audio/WuLiangYi/familybooklybook72.mp3"
            }, {
                "title": "证严法师讲述《无量义经》-73",
                "video": "audio/WuLiangYi/familybooklybook73.mp3"
            }, {
                "title": "证严法师讲述《无量义经》-74",
                "video": "audio/WuLiangYi/familybooklybook74.mp3"
            }, {
                "title": "证严法师讲述《无量义经》-75",
                "video": "audio/WuLiangYi/familybooklybook75.mp3"
            }, {
                "title": "证严法师讲述《无量义经》-76",
                "video": "audio/WuLiangYi/familybooklybook76.mp3"
            }, {
                "title": "证严法师讲述《无量义经》-77",
                "video": "audio/WuLiangYi/familybooklybook77.mp3"
            }, {
                "title": "证严法师讲述《无量义经》-78",
                "video": "audio/WuLiangYi/familybooklybook78.mp3"
            }]
        }]
    }
}